{
  "main": {
    "id": "48717a51e83d2aa5",
    "type": "split",
    "children": [
      {
        "id": "f39000b8145b19c1",
        "type": "tabs",
        "children": [
          {
            "id": "638d28d8e4eb2f10",
            "type": "leaf",
            "state": {
              "type": "markdown",
              "state": {
                "file": "Cesium.md",
                "mode": "source",
                "backlinks": false,
                "source": false
              }
            }
          }
        ]
      }
    ],
    "direction": "vertical"
  },
  "left": {
    "id": "4b2b71b62973b73c",
    "type": "split",
    "children": [
      {
        "id": "3a6ba7b67347a1b2",
        "type": "tabs",
        "children": [
          {
            "id": "0a50d9c573337de4",
            "type": "leaf",
            "state": {
              "type": "file-explorer",
              "state": {
                "sortOrder": "alphabetical"
              }
            }
          },
          {
            "id": "ae012ef0f7d93e48",
            "type": "leaf",
            "state": {
              "type": "search",
              "state": {
                "query": "",
                "matchingCase": false,
                "explainSearch": false,
                "collapseAll": false,
                "extraContext": false,
                "sortOrder": "alphabetical"
              }
            }
          },
          {
            "id": "abaa1e41f1f74ada",
            "type": "leaf",
            "state": {
              "type": "starred",
              "state": {}
            }
          }
        ],
        "currentTab": 1
      }
    ],
    "direction": "horizontal",
    "width": 300,
    "collapsed": true
  },
  "right": {
    "id": "6f6aee49d5407bee",
    "type": "split",
    "children": [
      {
        "id": "bc77cd9a3b8eb1bc",
        "type": "tabs",
        "children": [
          {
            "id": "3f5e35f3c2b63f92",
            "type": "leaf",
            "state": {
              "type": "tag",
              "state": {
                "sortOrder": "frequency",
                "useHierarchy": true
              }
            }
          },
          {
            "id": "6323b2f6898b32c7",
            "type": "leaf",
            "state": {
              "type": "git-view",
              "state": {}
            }
          },
          {
            "id": "c01e185f4aa3d7d3",
            "type": "leaf",
            "state": {
              "type": "outgoing-link",
              "state": {
                "file": "Cesium.md",
                "linksCollapsed": false,
                "unlinkedCollapsed": true
              }
            }
          },
          {
            "id": "5e55221e27be587d",
            "type": "leaf",
            "state": {
              "type": "backlink",
              "state": {
                "file": "Cesium.md",
                "collapseAll": false,
                "extraContext": false,
                "sortOrder": "alphabetical",
                "showSearch": false,
                "searchQuery": "",
                "backlinkCollapsed": false,
                "unlinkedCollapsed": true
              }
            }
          },
          {
            "id": "777c4cadf66f9b9d",
            "type": "leaf",
            "state": {
              "type": "git-history-view",
              "state": {}
            }
          }
        ],
        "currentTab": 1
      },
      {
        "id": "fa69ff743e95bac3",
        "type": "tabs",
        "children": [
          {
            "id": "a7974b07fd2b2c15",
            "type": "leaf",
            "state": {
              "type": "outline",
              "state": {
                "file": "Cesium.md"
              }
            }
          }
        ]
      }
    ],
    "direction": "horizontal",
    "width": 400.5,
    "collapsed": true
  },
  "left-ribbon": {
    "hiddenItems": {
      "markdown-importer:打开 Markdown 格式转换器": true,
      "switcher:打开快速切换": true,
      "graph:查看关系图谱": true,
      "canvas:新建白板": true,
      "daily-notes:打开/创建今天的日记": true,
      "templates:插入模板": true,
      "command-palette:打开命令面板": true
    }
  },
  "active": "6323b2f6898b32c7",
  "lastOpenFiles": [
    "WebGL.md",
    "Cesium.md",
    "Cesium-QA.md",
    "Web 3D.md",
    "images/Pasted image 20230419164035.png",
    "GIS OL Geoserver PostGIS.md",
    "WebGL-QA.md",
    "images/Pasted image 20230419101452.png",
    "images/Pasted image 20230419095100.png",
    "images/Pasted image 20230419095022.png",
    "images/Pasted image 20230411105231.png",
    "Cesium-3DTiles.md",
    "images/Pasted image 20230411101658.png",
    "Vue3.md",
    "conflict-files-obsidian-git.md",
    "☁.md",
    "杂-GPT-QA.md",
    "images/Pasted image 20230409173031.png",
    "AdBlock 规则.md",
    "Pasted image 20230411105231.png",
    "Pasted image 20230411104905.png",
    "Pasted image 20230411101658.png",
    "JS.md",
    "JS 进阶.md",
    "JS问答.md",
    "JS-TS.md",
    "KH.md",
    "HTTP.md",
    "Node.js.md",
    "nginx.md",
    "npm.md",
    "ThreeJS.md",
    "【通用】Git.md",
    "Python/【python】数据筛选.md",
    "Python/【python】实践.md",
    "Python",
    "投资 保险/images",
    "投资 保险",
    "images",
    "2 O/images",
    "2 O",
    "1 杂/images",
    "1 杂"
  ]
}